common_decorators/__init__.py
common_decorators/lazy.py
common_decorators-0.0.1.dist-info/LICENSE
common_decorators-0.0.1.dist-info/METADATA
common_decorators-0.0.1.dist-info/WHEEL
common_decorators-0.0.1.dist-info/top_level.txt
common_decorators-0.0.1.dist-info/RECORD
