Metadata-Version: 2.1
Name: common-decorators
Version: 0.0.1
Summary: Delightful Python decorators for daily use
Home-page: https://github.com/kaelzhang/python-common-decorators
Author: kaelzhang
Author-email: 
License: MIT
Keywords: common-decorators
Platform: UNKNOWN
Classifier: Topic :: Software Development :: Libraries :: Python Modules
Classifier: Programming Language :: Python :: 3.7
Classifier: Programming Language :: Python :: 3.8
Classifier: Programming Language :: Python :: Implementation :: PyPy
Classifier: Topic :: Software Development :: Libraries :: Python Modules
Classifier: License :: OSI Approved :: MIT License
Requires-Python: >=3.7
